.gitignore
MANIFEST.in
Makefile
README.md
setup.py
pylire/__init__.py
pylire.egg-info/PKG-INFO
pylire.egg-info/SOURCES.txt
pylire.egg-info/dependency_links.txt
pylire.egg-info/entry_points.txt
pylire.egg-info/not-zip-safe
pylire.egg-info/requires.txt
pylire.egg-info/top_level.txt
pylire/commands/__init__.py
pylire/commands/hashes.py
pylire/compatibility/__init__.py
pylire/compatibility/tests_jnius.py
pylire/compatibility/tests_jython.py
pylire/compatibility/utils.py
pylire/compatibility/libs/ae-awt.jar
pylire/compatibility/libs/commons-codec-1.9.jar
pylire/compatibility/libs/javax-imageio.jar
pylire/compatibility/libs/libreadline-java.jar
pylire/compatibility/libs/lire-request-handler.jar
pylire/compatibility/libs/lire.jar
pylire/compatibility/libs/notes.py
pylire/compatibility/libs/oortcloud.py
pylire/process/PHOG.py
pylire/process/__init__.py
pylire/process/bitsampling.py
pylire/process/channels.py
pylire/process/color_layout.py
pylire/process/edge_histogram.py
pylire/process/grayscale.py
pylire/process/opponent_histogram.py
pylire/process/bits/hash-functions.h5
pylire/process/ext/__init__.py
pylire/process/ext/channels.pyx
pylire/process/ext/grayscale.pyx
pylire/process/ext/opponent_histogram.pyx