Metadata-Version: 1.1
Name: pylire
Version: 0.3.8
Summary: Python/Cython port of Lire image processing algorithms
Home-page: http://github.com/fish2000/pylire/
Author: Alexander Bohn
Author-email: fish2000@gmail.com
License: GPLv2
Platform: UNKNOWN
Classifier: Development Status :: 4 - Beta
Classifier: Intended Audience :: Developers
Classifier: License :: OSI Approved :: BSD License
Classifier: Operating System :: OS Independent
Classifier: Programming Language :: Python
Classifier: Topic :: Utilities
